{
  "year": 115,
  "updated_at": "2026-07-02 03:21 UTC+8",
  "keywords": {
    "unsecured": "無擔保轉換公司債",
    "secured": "有擔保可轉換公司債"
  },
  "keep_months": 3,
  "total": 32,
  "records": [
    {
      "股票代碼": "2247",
      "公司名稱": "汎德永業",
      "市場別": "上市",
      "公告日期": "115/07/01",
      "序號": "3",
      "公告主旨": "公告本公司國內第二次無擔保轉換公司債轉換價格調整",
      "公告連結": "",
      "type": "unsecured"
    },
    {
      "股票代碼": "2247",
      "公司名稱": "汎德永業",
      "市場別": "上市",
      "公告日期": "115/07/01",
      "序號": "4",
      "公告主旨": "公告本公司國內第一次無擔保轉換公司債轉換價格調整",
      "公告連結": "",
      "type": "unsecured"
    },
    {
      "股票代碼": "2906",
      "公司名稱": "高林",
      "市場別": "上市",
      "公告日期": "115/07/01",
      "序號": "1",
      "公告主旨": "公告本公司國內第一次無擔保轉換公司債轉換價格調整",
      "公告連結": "",
      "type": "unsecured"
    },
    {
      "股票代碼": "3665",
      "公司名稱": "貿聯-KY",
      "市場別": "上市",
      "公告日期": "115/07/01",
      "序號": "1",
      "公告主旨": "公告本公司第六次海外無擔保轉換公司債轉換價格調整",
      "公告連結": "",
      "type": "unsecured"
    },
    {
      "股票代碼": "8021",
      "公司名稱": "尖點",
      "市場別": "上市",
      "公告日期": "115/07/01",
      "序號": "3",
      "公告主旨": "公告本公司國內第二次無擔保轉換公司債轉換價格調整",
      "公告連結": "",
      "type": "unsecured"
    },
    {
      "股票代碼": "3219",
      "公司名稱": "倚強科",
      "市場別": "上櫃",
      "公告日期": "115/07/01",
      "序號": "1",
      "公告主旨": "公告本公司董事會決議辦理發行國內第一次無擔保轉換公司債",
      "公告連結": "",
      "type": "unsecured"
    },
    {
      "股票代碼": "3551",
      "公司名稱": "世禾",
      "市場別": "上櫃",
      "公告日期": "115/07/01",
      "序號": "2",
      "公告主旨": "公告本公司國內第三次無擔保轉換公司債轉換價格調整",
      "公告連結": "",
      "type": "unsecured"
    },
    {
      "股票代碼": "3016",
      "公司名稱": "嘉晶",
      "市場別": "上市",
      "公告日期": "115/06/30",
      "序號": "2",
      "公告主旨": "公告本公司董事會決議發行國內第六次無擔保轉換公司債",
      "公告連結": "",
      "type": "unsecured"
    },
    {
      "股票代碼": "7610",
      "公司名稱": "聯友金屬-創",
      "市場別": "上市",
      "公告日期": "115/06/30",
      "序號": "1",
      "公告主旨": "補充公告本公司國內第一次無擔保轉換公司債轉換價格調整",
      "公告連結": "",
      "type": "unsecured"
    },
    {
      "股票代碼": "3587",
      "公司名稱": "閎康",
      "市場別": "上櫃",
      "公告日期": "115/06/30",
      "序號": "1",
      "公告主旨": "公告本公司董事長決議除息基準日及國內第二\r\n次無擔保轉換公司債停止轉換期間",
      "公告連結": "",
      "type": "unsecured"
    },
    {
      "股票代碼": "5289",
      "公司名稱": "宜鼎",
      "市場別": "上櫃",
      "公告日期": "115/06/30",
      "序號": "1",
      "公告主旨": "公告本公司國內第二次無擔保轉換公司債收足應募價款",
      "公告連結": "",
      "type": "unsecured"
    },
    {
      "股票代碼": "8096",
      "公司名稱": "擎亞",
      "市場別": "上櫃",
      "公告日期": "115/06/30",
      "序號": "1",
      "公告主旨": "公告本公司國內第二次無擔保轉換公司債收足債款",
      "公告連結": "",
      "type": "unsecured"
    },
    {
      "股票代碼": "1623",
      "公司名稱": "大東電",
      "市場別": "上市",
      "公告日期": "115/06/29",
      "序號": "1",
      "公告主旨": "公告本公司發行國內第一次無擔保轉換公司債之代收價款\r\n行庫及存儲專戶行庫",
      "公告連結": "",
      "type": "unsecured"
    },
    {
      "股票代碼": "7610",
      "公司名稱": "聯友金屬-創",
      "市場別": "上市",
      "公告日期": "115/06/29",
      "序號": "1",
      "公告主旨": "公告本公司國內第一次無擔保轉換公司債轉換價格調整",
      "公告連結": "",
      "type": "unsecured"
    },
    {
      "股票代碼": "6570",
      "公司名稱": "維田",
      "市場別": "上櫃",
      "公告日期": "115/06/29",
      "序號": "1",
      "公告主旨": "公告本公司董事會決議發行國內第二次無擔保轉換公司債",
      "公告連結": "",
      "type": "unsecured"
    },
    {
      "股票代碼": "6890",
      "公司名稱": "來億-KY",
      "市場別": "上市",
      "公告日期": "115/06/26",
      "序號": "1",
      "公告主旨": "公告本公司國內第一次無擔保轉換公司債轉換價格調整",
      "公告連結": "",
      "type": "unsecured"
    },
    {
      "股票代碼": "6890",
      "公司名稱": "來億-KY",
      "市場別": "上市",
      "公告日期": "115/06/26",
      "序號": "2",
      "公告主旨": "公告本公司國內第二次無擔保轉換公司債轉換價格調整",
      "公告連結": "",
      "type": "unsecured"
    },
    {
      "股票代碼": "4129",
      "公司名稱": "聯合",
      "市場別": "上櫃",
      "公告日期": "115/06/26",
      "序號": "2",
      "公告主旨": "公告聯合骨科器材股份有限公司國內第五次無擔保轉換公司債(例：第一次有擔保)轉(交)換公司債(簡稱：聯合五，代碼：41295)停止受理轉交換等相關事項。",
      "公告連結": "",
      "type": "unsecured"
    },
    {
      "股票代碼": "6179",
      "公司名稱": "亞通",
      "市場別": "上櫃",
      "公告日期": "115/06/26",
      "序號": "2",
      "公告主旨": "公告本公司第三次無擔保轉換公司債停止受理轉換及到期日\r\n落於停止轉換期間相關事項之公告不再適用",
      "公告連結": "",
      "type": "unsecured"
    },
    {
      "股票代碼": "1589",
      "公司名稱": "永冠-KY",
      "市場別": "上市",
      "公告日期": "115/06/25",
      "序號": "1",
      "公告主旨": "公告本公司中華民國境內第四次無擔保轉換公司債(簡稱：永冠\r\n四KY，代碼：15894)訂於115年6月29日終止櫃檯買賣",
      "公告連結": "",
      "type": "unsecured"
    },
    {
      "股票代碼": "3028",
      "公司名稱": "增你強",
      "市場別": "上市",
      "公告日期": "115/06/25",
      "序號": "1",
      "公告主旨": "公告本公司簽訂國內第五次無擔保轉換公司債暨國內第六次\r\n無擔保轉換公司債之代收價款及存儲價款合約",
      "公告連結": "",
      "type": "unsecured"
    },
    {
      "股票代碼": "3711",
      "公司名稱": "日月光投控",
      "市場別": "上市",
      "公告日期": "115/06/25",
      "序號": "3",
      "公告主旨": "本公司董事會決議通過發行海外第一次無擔保轉換公司債",
      "公告連結": "",
      "type": "unsecured"
    },
    {
      "股票代碼": "6830",
      "公司名稱": "汎銓",
      "市場別": "上市",
      "公告日期": "115/06/25",
      "序號": "2",
      "公告主旨": "公告汎銓科技股份有限公司第一次無擔保轉換公司債\r\n(簡稱：汎銓一，代碼：68301)於櫃檯買賣市場交易達公布\r\n注意交易資訊標準，故公布相關訊息，以利投資人區別瞭解。",
      "公告連結": "",
      "type": "unsecured"
    },
    {
      "股票代碼": "6274",
      "公司名稱": "台燿",
      "市場別": "上櫃",
      "公告日期": "115/06/24",
      "序號": "1",
      "公告主旨": "本公司國內第五次無擔保轉換公司債台燿五(代號:62745)\r\n近期達公布注意交易資訊標準，公告相關訊息，以利投資人\r\n區別瞭解",
      "公告連結": "",
      "type": "unsecured"
    },
    {
      "股票代碼": "8096",
      "公司名稱": "擎亞",
      "市場別": "上櫃",
      "公告日期": "115/06/24",
      "序號": "1",
      "公告主旨": "公告本公司國內第二次無擔保轉換公司債之轉換價格及\r\n溢價率",
      "公告連結": "",
      "type": "unsecured"
    },
    {
      "股票代碼": "8096",
      "公司名稱": "擎亞",
      "市場別": "上櫃",
      "公告日期": "115/06/24",
      "序號": "2",
      "公告主旨": "公告本公司國內第三次無擔保轉換公司債之轉換價格及\r\n溢價率",
      "公告連結": "",
      "type": "unsecured"
    },
    {
      "股票代碼": "8147",
      "公司名稱": "正淩",
      "市場別": "上櫃",
      "公告日期": "115/06/24",
      "序號": "2",
      "公告主旨": "公告本公司國內第三次無擔保轉換公司債轉換價格調整",
      "公告連結": "",
      "type": "unsecured"
    },
    {
      "股票代碼": "6584",
      "公司名稱": "南俊國際",
      "市場別": "上櫃",
      "公告日期": "115/06/23",
      "序號": "1",
      "公告主旨": "公告本公司簽訂發行第三次無擔保轉換公司債代收股款行庫\r\n及存儲專戶",
      "公告連結": "",
      "type": "unsecured"
    },
    {
      "股票代碼": "6693",
      "公司名稱": "廣閎科",
      "市場別": "上櫃",
      "公告日期": "115/06/23",
      "序號": "1",
      "公告主旨": "公告本公司發行國內第一次無擔保轉換公司債之\r\n委託代收價款行庫及存儲專戶行庫",
      "公告連結": "",
      "type": "unsecured"
    },
    {
      "股票代碼": "6840",
      "公司名稱": "東研信超",
      "市場別": "上櫃",
      "公告日期": "115/06/22",
      "序號": "3",
      "公告主旨": "公告本公司國內第一次無擔保轉換公司債轉換價格調整",
      "公告連結": "",
      "type": "unsecured"
    },
    {
      "股票代碼": "3191",
      "公司名稱": "雲嘉南",
      "市場別": "上櫃",
      "公告日期": "115/05/13",
      "序號": "3",
      "公告主旨": "本公司董事會決議不繼續辦理114年度私募普通股及國內\r\n有擔保可轉換公司債。",
      "公告連結": "",
      "type": "secured"
    },
    {
      "股票代碼": "2461",
      "公司名稱": "光群雷",
      "市場別": "上市",
      "公告日期": "115/04/09",
      "序號": "1",
      "公告主旨": "本公司國內第六次有擔保可轉換公司債轉換普通股",
      "公告連結": "",
      "type": "secured"
    }
  ]
}